rednest/__init__.py
rednest/dictionary.py
rednest/encoder.py
rednest/list.py
rednest/nested.py
rednest/py.typed
rednest-0.7.0.dist-info/LICENSE
rednest-0.7.0.dist-info/METADATA
rednest-0.7.0.dist-info/WHEEL
rednest-0.7.0.dist-info/top_level.txt
rednest-0.7.0.dist-info/RECORD
