Metadata-Version: 2.1
Name: rednest
Version: 0.7.0
Summary: Redis dictionary & list nesting for Python objects
Maintainer-email: Nadav Tasher <hey@nadav.app>
License: MIT License
Project-URL: Homepage, https://github.com/NadavTasher/RedNest
Keywords: redis,rejson,database,dict
Classifier: License :: OSI Approved :: MIT License
Classifier: Programming Language :: Python :: 3
License-File: LICENSE
Requires-Dist: redis >=5.0.0
